ulam/__init__.py
ulam/spiral.py
ulam/triangle.py
ulam_spiral-1.2.dist-info/DESCRIPTION.rst
ulam_spiral-1.2.dist-info/METADATA
ulam_spiral-1.2.dist-info/RECORD
ulam_spiral-1.2.dist-info/WHEEL
ulam_spiral-1.2.dist-info/metadata.json
ulam_spiral-1.2.dist-info/top_level.txt
