Metadata-Version: 2.0
Name: ulam-spiral
Version: 1.2
Summary: Ulam spiral
Home-page: https://gitlab.com/VadVergasov/ulam
Author: VadVergasov
Author-email: vadim.vergasov2003@gmail.com
License: MIT
Keywords: ulam spiral numbers
Platform: any
Requires-Dist: pillow
